pypstruct/__init__.py
pypstruct/contact_map_pure.py
pypstruct/coordinates.py
pypstruct/operations.py
pypstruct-0.1.2.dist-info/LICENSE
pypstruct-0.1.2.dist-info/WHEEL
pypstruct-0.1.2.dist-info/METADATA
pypstruct-0.1.2.dist-info/RECORD
